microsoft_drive_mcpserver/__init__.py
microsoft_drive_mcpserver/drive.py
microsoft_drive_mcpserver/server.py
microsoft_drive_mcpserver-0.1.4.dist-info/LICENSE
microsoft_drive_mcpserver-0.1.4.dist-info/METADATA
microsoft_drive_mcpserver-0.1.4.dist-info/WHEEL
microsoft_drive_mcpserver-0.1.4.dist-info/entry_points.txt
microsoft_drive_mcpserver-0.1.4.dist-info/RECORD
